srcnlpbg/__init__.py
srcnlpbg/inference/__init__.py
srcnlpbg/inference/predictor.py
srcnlpbg/machine_translation/__init__.py
srcnlpbg/machine_translation/translation.py
srcnlpbg/main.py
srcnlpbg/output/__init__.py
srcnlpbg/output/output.py
srcnlpbg/README.md
srcnlpbg/transcription/__init__.py
srcnlpbg/transcription/transcription.py
srcnlpbg-0.0.1.dist-info/METADATA
srcnlpbg-0.0.1.dist-info/WHEEL
srcnlpbg-0.0.1.dist-info/RECORD
